wsignals/__init__.py
wsignals/signals.py
wsignals-0.2.3.dist-info/METADATA
wsignals-0.2.3.dist-info/WHEEL
wsignals-0.2.3.dist-info/licenses/LICENSE
wsignals-0.2.3.dist-info/RECORD
