Metadata-Version: 2.4
Name: wsignals
Version: 0.2.3
Summary: Library for event emitting and handling
Project-URL: Homepage, https://github.com/wumtdev/wsignals
Author: WuMT
License-Expression: MIT
License-File: LICENSE
Requires-Python: >=3.6
